.coveragerc
.mailmap
.testr.conf
AUTHORS
CONTRIBUTING.rst
ChangeLog
LICENSE
MANIFEST.in
README.rst
requirements.txt
setup.cfg
setup.py
test-requirements.txt
tox.ini
doc/source/conf.py
doc/source/contributing.rst
doc/source/index.rst
doc/source/installation.rst
doc/source/readme.rst
doc/source/usage.rst
splitter/__init__.py
splitter/splitter.py
splitter.egg-info/PKG-INFO
splitter.egg-info/SOURCES.txt
splitter.egg-info/dependency_links.txt
splitter.egg-info/entry_points.txt
splitter.egg-info/not-zip-safe
splitter.egg-info/requires.txt
splitter.egg-info/top_level.txt
splitter/tests/__init__.py
splitter/tests/base.py
splitter/tests/test_splitter.py
splitter/tests/text-english.txt
splitter/tests/text-french.txt